spaceone/__init__.py
spaceone/api/__init__.py
spaceone/api/alert_manager/__init__.py
spaceone/api/alert_manager/plugin/__init__.py
spaceone/api/alert_manager/plugin/event_pb2.py
spaceone/api/alert_manager/plugin/event_pb2_grpc.py
spaceone/api/alert_manager/plugin/notification_pb2.py
spaceone/api/alert_manager/plugin/notification_pb2_grpc.py
spaceone/api/alert_manager/plugin/protocol_pb2.py
spaceone/api/alert_manager/plugin/protocol_pb2_grpc.py
spaceone/api/alert_manager/plugin/webhook_pb2.py
spaceone/api/alert_manager/plugin/webhook_pb2_grpc.py
spaceone/api/alert_manager/v1/__init__.py
spaceone/api/alert_manager/v1/alert_pb2.py
spaceone/api/alert_manager/v1/alert_pb2_grpc.py
spaceone/api/alert_manager/v1/escalation_policy_pb2.py
spaceone/api/alert_manager/v1/escalation_policy_pb2_grpc.py
spaceone/api/alert_manager/v1/event_pb2.py
spaceone/api/alert_manager/v1/event_pb2_grpc.py
spaceone/api/alert_manager/v1/event_rule_pb2.py
spaceone/api/alert_manager/v1/event_rule_pb2_grpc.py
spaceone/api/alert_manager/v1/note_pb2.py
spaceone/api/alert_manager/v1/note_pb2_grpc.py
spaceone/api/alert_manager/v1/notification_protocol_pb2.py
spaceone/api/alert_manager/v1/notification_protocol_pb2_grpc.py
spaceone/api/alert_manager/v1/service_channel_pb2.py
spaceone/api/alert_manager/v1/service_channel_pb2_grpc.py
spaceone/api/alert_manager/v1/service_pb2.py
spaceone/api/alert_manager/v1/service_pb2_grpc.py
spaceone/api/alert_manager/v1/user_channel_pb2.py
spaceone/api/alert_manager/v1/user_channel_pb2_grpc.py
spaceone/api/alert_manager/v1/user_group_channel_pb2.py
spaceone/api/alert_manager/v1/user_group_channel_pb2_grpc.py
spaceone/api/alert_manager/v1/webhook_pb2.py
spaceone/api/alert_manager/v1/webhook_pb2_grpc.py
spaceone/api/board/__init__.py
spaceone/api/board/v1/__init__.py
spaceone/api/board/v1/post_pb2.py
spaceone/api/board/v1/post_pb2_grpc.py
spaceone/api/config/__init__.py
spaceone/api/config/v1/__init__.py
spaceone/api/config/v1/domain_config_pb2.py
spaceone_api-2.0.435.dist-info/METADATA
spaceone_api-2.0.435.dist-info/WHEEL
spaceone_api-2.0.435.dist-info/top_level.txt
spaceone_api-2.0.435.dist-info/RECORD
