Metadata-Version: 2.1
Name: spaceone-api
Version: 2.0.435
Summary: Coreforet API Protobuf
Home-page: https://cloudforet.io/
Author: MEGAZONE Cloud Corp.
Author-email: admin@spaceone.dev
License: Apache Software License
Platform: UNKNOWN
